<?xml version="1.0" encoding="utf-8"?>
<openerp>
    <data>

        <!-- FORM VIEW -->
        <record id="view_pos_session_form" model="ir.ui.view">
            <field name="name">pos.session.form</field>
            <field name="model">pos.session</field>
            <field name="inherit_id" ref="point_of_sale.view_pos_session_form"/>
            <field name="arch" type="xml">

                <xpath expr="//header/button[@name='close']" position="after">
                    <field name="is_fiscal" invisible="1"/>
                    <button name="test_uno" type="object"
                            string="TEST"
                            states="opened"
                    attrs="{'invisible': [('is_fiscal', '=', 0)]}"/>
                </xpath>

            </field>
        </record>

    </data>
</openerp>