<?xml version="1.0" encoding="utf-8"?>
<openerp>
    <data noupdate="0">

        <!-- Cron data -->
        <record id="bulonfer_cron_data" model="ir.cron">
            <field name="name">Importar datos Bulonfer</field>
            <field name="interval_type">work_days</field>
            <field name="model">product_autoload.manager</field>
            <field name="function">run</field>
            <field name="args"></field>
        </record>

        <!-- Cron data -->
        <record id="bulonfer_cron_categ" model="ir.cron">
            <field name="name">Generar categorias Bulonfer</field>
            <field name="interval_type">minutes</field>
            <field name="model">product_autoload.manager</field>
            <field name="function">update_categories</field>
            <field name="args"></field>
        </record>

    </data>
</openerp>
